atlasai/discovery/client/.env
atlasai/discovery/client/__init__.py
atlasai/discovery/client/constants.py
atlasai/discovery/client/endpoint.py
atlasai/discovery/client/environ.py
atlasai/discovery/client/helpers.py
atlasai/discovery/client/init.py
atlasai/discovery/client/instances.py
atlasai/discovery/client/misc.py
atlasai/discovery/client/namespace.py
atlasai/discovery/client/other.py
atlasai/discovery/client/product.py
atlasai/discovery/client/products.py
atlasai/discovery/client/reference.py
atlasai/discovery/client/releases.py
atlasai/discovery/client/retry.py
atlasai/discovery/client/schema.py
atlasai/discovery/client/tags.py
atlasai/discovery/client/utils.py
atlasai/discovery/client/instance/__init__.py
atlasai/discovery/client/instance/parents.py
atlasai/discovery/client/release/__init__.py
atlasai/discovery/client/release/instances.py
atlasai_discovery_client-1.15.2.dist-info/LICENSE.txt
atlasai_discovery_client-1.15.2.dist-info/METADATA
atlasai_discovery_client-1.15.2.dist-info/WHEEL
atlasai_discovery_client-1.15.2.dist-info/top_level.txt
atlasai_discovery_client-1.15.2.dist-info/RECORD
