Metadata-Version: 2.1
Name: atlasai-discovery-client
Version: 1.15.2
Summary: UNKNOWN
Home-page: UNKNOWN
Author: AtlasAI SWE
Author-email: swe@atlasai.co
License: UNKNOWN
Platform: UNKNOWN
Requires-Python: >=3.8
License-File: LICENSE.txt
Requires-Dist: arrow (<2.0.0,>=1.2.2)
Requires-Dist: atlasai-sgqlc (~=16.3.0)
Requires-Dist: atlasai-vinz-client
Requires-Dist: furl (<3.0.0,>=2.1.0)
Requires-Dist: google-cloud-storage (<3.0.0,>=2.8.0)
Requires-Dist: python-dotenv (<2.0.0,>=1.0.0)
Requires-Dist: requests (<=3.0.0,>=2.28.0)
Requires-Dist: semver (<4.0.0,>=3.0.0)
Requires-Dist: shapely (<3.0.0,>=2.0.0)
Provides-Extra: dev
Requires-Dist: coverage ; extra == 'dev'
Requires-Dist: flake8 ; extra == 'dev'
Requires-Dist: ipdb ; extra == 'dev'
Requires-Dist: ipython ; extra == 'dev'
Requires-Dist: line-profiler ; extra == 'dev'
Requires-Dist: memory-profiler ; extra == 'dev'
Requires-Dist: mock ; extra == 'dev'
Requires-Dist: pycallgraph2 ; extra == 'dev'
Requires-Dist: pytest ; extra == 'dev'
Requires-Dist: pytest-cov ; extra == 'dev'
Requires-Dist: requests-mock ; extra == 'dev'
Requires-Dist: twine ; extra == 'dev'
Provides-Extra: dist
Requires-Dist: twine ; extra == 'dist'
Provides-Extra: test
Requires-Dist: coverage ; extra == 'test'
Requires-Dist: mock ; extra == 'test'
Requires-Dist: pytest ; extra == 'test'
Requires-Dist: pytest-cov ; extra == 'test'
Requires-Dist: requests-mock ; extra == 'test'
